pvkoala/LICENSE
pvkoala/__init__.py
pvkoala/_factory.py
pvkoala/_koala.py
pvkoala/_util.py
pvkoala/lib/common/koala_params.pv
pvkoala/lib/linux/x86_64/libpv_koala.so
pvkoala/lib/mac/arm64/libpv_koala.dylib
pvkoala/lib/mac/x86_64/libpv_koala.dylib
pvkoala/lib/raspberry-pi/cortex-a53/libpv_koala.so
pvkoala/lib/raspberry-pi/cortex-a53-aarch64/libpv_koala.so
pvkoala/lib/raspberry-pi/cortex-a72/libpv_koala.so
pvkoala/lib/raspberry-pi/cortex-a72-aarch64/libpv_koala.so
pvkoala/lib/raspberry-pi/cortex-a76/libpv_koala.so
pvkoala/lib/raspberry-pi/cortex-a76-aarch64/libpv_koala.so
pvkoala/lib/windows/amd64/libpv_koala.dll
pvkoala/lib/windows/amd64/pv_ypu_impl_cuda.dll
pvkoala/lib/windows/arm64/libpv_koala.dll
pvkoala-3.0.0.dist-info/METADATA
pvkoala-3.0.0.dist-info/WHEEL
pvkoala-3.0.0.dist-info/top_level.txt
pvkoala-3.0.0.dist-info/RECORD
