Metadata-Version: 2.1
Name: pvkoala
Version: 3.0.0
Summary: Koala Noise Suppression Engine.
Home-page: https://github.com/Picovoice/koala
Author: Picovoice
Author-email: hello@picovoice.ai
Keywords: Noise Cancellation,Noise Suppression,Noise Removal,Speech Enhancement,Speech Denoising
Classifier: Development Status :: 5 - Production/Stable
Classifier: Intended Audience :: Developers
Classifier: License :: OSI Approved :: Apache Software License
Classifier: Operating System :: OS Independent
Classifier: Programming Language :: Python :: 3
Classifier: Topic :: Multimedia :: Sound/Audio :: Speech
Requires-Python: >=3.9
